neutrino_cli/__init__.py
neutrino_cli/__version__.py
neutrino_cli/neutrino_cli.py
neutrino_cli/compiler/__init__.py
neutrino_cli/compiler/build_setup.py
neutrino_cli/compiler/compiler.py
neutrino_cli/compiler/file_utilities.py
neutrino_cli/compiler/ignore_handler.py
neutrino_cli/compiler/templates/__init__.py
neutrino_cli/compiler/templates/template.py
neutrino_cli/compiler/templates/config_template/__init__.py
neutrino_cli/compiler/templates/config_template/config_template.py
neutrino_cli/compiler/templates/dockerfile_template/__init__.py
neutrino_cli/compiler/templates/dockerfile_template/dockerfile_template.py
neutrino_cli/compiler/templates/init_py_template/__init__.py
neutrino_cli/compiler/templates/init_py_template/init_py_template.py
neutrino_cli/compiler/templates/main_template/__init__.py
neutrino_cli/compiler/templates/main_template/main_template.py
neutrino_cli/compiler/templates/neutrino_config_template/__init__.py
neutrino_cli/compiler/templates/neutrino_config_template/neutrino_config_template.py
neutrino_cli/compiler/templates/neutrinoignore_template/__init__.py
neutrino_cli/compiler/templates/neutrinoignore_template/neutrinoignore_template.py
neutrino_cli/compiler/templates/requirements_template/__init__.py
neutrino_cli/compiler/templates/requirements_template/requirements_template.py
neutrino_cli/compiler/templates/scheduler_template/__init__.py
neutrino_cli/compiler/templates/scheduler_template/scheduler_template.py
neutrino_cli/compiler/templates/start_script_template/__init__.py
neutrino_cli/compiler/templates/start_script_template/start_script_template.py
neutrino_cli/compiler/templates/websockets_manager_template/__init__.py
neutrino_cli/compiler/templates/websockets_manager_template/websockets_manager_template.py
neutrino_cli/parser/__init__.py
neutrino_cli/parser/parser.py
neutrino_cli/parser/cells/__init__.py
neutrino_cli/parser/cells/cell.py
neutrino_cli/parser/cells/code_cell.py
neutrino_cli/parser/cells/http_cell.py
neutrino_cli-0.1.13.dist-info/LICENSE
neutrino_cli-0.1.13.dist-info/METADATA
neutrino_cli-0.1.13.dist-info/WHEEL
neutrino_cli-0.1.13.dist-info/entry_points.txt
neutrino_cli-0.1.13.dist-info/top_level.txt
neutrino_cli-0.1.13.dist-info/RECORD
