Metadata-Version: 2.1
Name: neutrino-cli
Version: 0.1.13
License-File: LICENSE
Requires-Dist: click
Requires-Dist: nbformat
Requires-Dist: autopep8
Requires-Dist: python-dotenv
Requires-Dist: termcolor
Requires-Dist: Jinja2
Requires-Dist: PyYAML
Requires-Dist: requests
